[{"id":5,"type":"note","title":"not1","content":"some234!","date":"May 28, 2023","time":"08:39 PM"},{"id":6,"type":"event","title":"eve34","content":"some23fdhfh ","date":"May 28, 2023","time":"08:51 PM","eventDate":"2023-12-14"},{"id":7,"type":"task","title":"tsk3","content":"tsk3","date":"May 16, 2023","time":"06:41 PM","dueDate":"2023-05-04","isCompleted":true},{"id":11,"type":"task","title":"tsk4","content":"dfdsfsdkkkkkkkkkk dkvjhds kdsjhdslkjds dslidjsfk","date":"May 16, 2023","time":"04:49 PM","dueDate":"2023-05-12","isCompleted":false},{"id":12,"type":"task","title":"tsk5","content":"tsk4","date":"May 15, 2023","time":"08:13 PM","dueDate":"2023-05-09","isCompleted":false},{"id":13,"type":"event","title":"bbvv","content":"fdfdf","date":"May 28, 2023","time":"08:39 PM","eventDate":"2023-05-10"},{"id":14,"type":"event","title":"xzczxc dsf sdjk dflkj","content":"cscsdvdv sxkjhdsjh dslfkjsdflkjdsf osidfjsdkf asdkjsa d;kjsadkjsda sadlkjds asdlkjsda saldkjsd saldkj ","date":"May 28, 2023","time":"08:39 PM","eventDate":"2024-05-24"},{"id":15,"type":"task","title":"tsk1","content":"tsk1","date":"May 15, 2023","time":"08:12 PM","dueDate":"2023-05-20","isCompleted":false},{"id":16,"type":"task","title":"tsk2","content":"tsk22","date":"May 15, 2023","time":"10:21 PM","dueDate":"2023-05-17","isCompleted":false},{"id":18,"type":"task","title":"tsk72","content":"tsk7","date":"May 15, 2023","time":"10:21 PM","dueDate":"2023-05-20","isCompleted":false},{"id":19,"type":"task","title":"tsk8","content":"tsk8","date":"May 15, 2023","time":"08:14 PM","dueDate":"2023-05-19","isCompleted":false},{"id":23,"type":"note","title":"fdfdf","content":"sdfsdf","date":"May 16, 2023","time":"06:24 PM"},{"id":24,"type":"note","title":"fdgdf","content":"fgdfg","date":"May 16, 2023","time":"06:42 PM"},{"id":25,"type":"note","title":"vdsv","content":"fffdf","date":"May 17, 2023","time":"10:04 PM"}]